pip_services4_postgres/__init__.py
pip_services4_postgres/build/DefaultPostgresFactory.py
pip_services4_postgres/build/__init__.py
pip_services4_postgres/connect/PostgresConnection.py
pip_services4_postgres/connect/PostgresConnectionResolver.py
pip_services4_postgres/connect/__init__.py
pip_services4_postgres/persistence/IdentifiableJsonPostgresPersistence.py
pip_services4_postgres/persistence/IdentifiablePostgresPersistence.py
pip_services4_postgres/persistence/PostgresPersistence.py
pip_services4_postgres/persistence/__init__.py
pip_services4_postgres-0.0.1.dist-info/METADATA
pip_services4_postgres-0.0.1.dist-info/WHEEL
pip_services4_postgres-0.0.1.dist-info/top_level.txt
pip_services4_postgres-0.0.1.dist-info/zip-safe
pip_services4_postgres-0.0.1.dist-info/RECORD
